aocp/__init__.py
aocp/parsers.py
aocp-0.1.1.dist-info/LICENSE
aocp-0.1.1.dist-info/WHEEL
aocp-0.1.1.dist-info/METADATA
aocp-0.1.1.dist-info/RECORD
